hivemcapi/__init__.py
hivemcapi/cft.py
hivemcapi/deathrun.py
hivemcapi/drop.py
hivemcapi/ground.py
hivemcapi/hideseek.py
hivemcapi/murder.py
hivemcapi/sg.py
hivemcapi/swars.py
hivemcapi/twars.py
hivemcapi-2.1.dist-info/METADATA
hivemcapi-2.1.dist-info/WHEEL
hivemcapi-2.1.dist-info/top_level.txt
hivemcapi-2.1.dist-info/RECORD
