Metadata-Version: 2.1
Name: hivemcapi
Version: 2.1
Summary: A api rapper for the hivemc api
Home-page: https://github.com/Nagol12344/HiveMCapi/
Author: Nagol12344
Author-email: Hidden@hidden.com
License: MIT
Download-URL: https://github.com/Nagol12344/HiveMCapi/releases/latest/
Project-URL: Bug Tracker, https://github.com/Nagol12344/HiveMCapi/issues
Keywords: hivemc,api,hivemcapi
Platform: UNKNOWN
Classifier: Development Status :: 4 - Beta
Classifier: Intended Audience :: Developers
Classifier: Topic :: Software Development
Classifier: License :: OSI Approved :: MIT License
Classifier: Programming Language :: Python :: 3
Classifier: Programming Language :: Python :: 3.4
Classifier: Programming Language :: Python :: 3.5
Classifier: Programming Language :: Python :: 3.6
Classifier: Programming Language :: Python :: 3.7
Classifier: Programming Language :: Python :: 3.8
Classifier: Programming Language :: Python :: 3.9
Classifier: Programming Language :: Python :: 3.10
Requires-Dist: requests
